gwtc/__init__.py
gwtc/_version.py
gwtc/gwtc.py
gwtc/gwtc_create_from_query.py
gwtc/gwtc_diff.py
gwtc/gwtc_get_gevent_coinc_files.py
gwtc/gwtc_gracedb.py
gwtc/gwtc_revert.py
gwtc/gwtc_update_pipeline_gevents.py
gwtc_tools-0.3.1.dist-info/licenses/LICENSE.md
gwtc_tools-0.3.1.dist-info/METADATA
gwtc_tools-0.3.1.dist-info/WHEEL
gwtc_tools-0.3.1.dist-info/entry_points.txt
gwtc_tools-0.3.1.dist-info/top_level.txt
gwtc_tools-0.3.1.dist-info/RECORD
