Metadata-Version: 2.4
Name: gwtc-tools
Version: 0.3.1
Summary: A package for gwtc operations, including interactions with gracedb
Home-page: https://git.ligo.org/chad-hanna/gwtc
Author: Chad Hanna
Author-email: Chad Hanna <chad.hanna@ligo.org>, Alexander Pace <alexander.pace@ligo.org>, Divya Singh <divya.singh@ligo.org>, Leo Tsukada <leo.tsukada@ligo.org>, Patrick Godwin <patrick.godwin@ligo.org>, Prathamesh Joshi <prathamesh.joshi@ligo.org>, Becca Ewing <rebecca.ewing@ligo.org>, Rhiannon Udall <rhiannon.udall@ligo.org>
Project-URL: Homepage, https://git.ligo.org/chad-hanna/gwtc
Project-URL: Bug Tracker, https://git.ligo.org/chad-hanna/gwtc/-/issues
Classifier: Programming Language :: Python :: 3
Classifier: License :: OSI Approved :: MIT License
Classifier: Operating System :: OS Independent
Requires-Python: >=3.6
License-File: LICENSE.md
Requires-Dist: ligo-gracedb
Requires-Dist: pyyaml
Dynamic: license-file
